unicef_sharepoint/__init__.py
unicef_sharepoint/admin.py
unicef_sharepoint/apps.py
unicef_sharepoint/client.py
unicef_sharepoint/config.py
unicef_sharepoint/filters.py
unicef_sharepoint/models.py
unicef_sharepoint/serializers.py
unicef_sharepoint/urls.py
unicef_sharepoint/utils.py
unicef_sharepoint/views.py
unicef_sharepoint/lib/__init__.py
unicef_sharepoint/migrations/0001_initial.py
unicef_sharepoint/migrations/__init__.py
unicef_sharepoint-0.3.dist-info/METADATA
unicef_sharepoint-0.3.dist-info/WHEEL
unicef_sharepoint-0.3.dist-info/top_level.txt
unicef_sharepoint-0.3.dist-info/RECORD
