Metadata-Version: 2.1
Name: unicef-sharepoint
Version: 0.3
Summary: Provides Basic Unicef User model and integration with Azure
Home-page: https://github.com/unicef/unicef-sharepoint
Author: UNICEF
Author-email: rapidpro@unicef.org
License: Apache 2 License
Platform: any
Classifier: Environment :: Web Environment
Classifier: Programming Language :: Python :: 3.8
Classifier: Framework :: Django
Classifier: Framework :: Django :: 3.0
Classifier: Intended Audience :: Developers
Requires-Dist: django
Requires-Dist: django-filter
Requires-Dist: django-model-utils
Requires-Dist: djangorestframework
Requires-Dist: office365-rest-client
Provides-Extra: test
Requires-Dist: django-webtest ; extra == 'test'
Requires-Dist: factory-boy ; extra == 'test'
Requires-Dist: flake8 ; extra == 'test'
Requires-Dist: isort ; extra == 'test'
Requires-Dist: mock ; extra == 'test'
Requires-Dist: pytest ; extra == 'test'
Requires-Dist: pytest-cov ; extra == 'test'
Requires-Dist: pytest-django ; extra == 'test'
Requires-Dist: pytest-echo ; extra == 'test'
Requires-Dist: pytest-pythonpath ; extra == 'test'
Requires-Dist: pytest-redis ; extra == 'test'
Requires-Dist: requests-mock ; extra == 'test'
Requires-Dist: unittest2 ; extra == 'test'
Requires-Dist: vcrpy ; extra == 'test'
Requires-Dist: drf-api-checker ; extra == 'test'
